{"n_iters": 10000, "Overall": {"AUC of ROC": {"value": 0.872284, "mean": 0.872731, "median": 0.873258, "std": 0.016847, "2.5% percentile": 0.838595, "97.5% percentile": 0.90413}, "AUC of PRC": {"value": 0.497484, "mean": 0.500229, "median": 0.500655, "std": 0.054287, "2.5% percentile": 0.393904, "97.5% percentile": 0.605624}, "min(+P, Se)": {"value": 0.5, "mean": 0.511052, "median": 0.511905, "std": 0.042914, "2.5% percentile": 0.425526, "97.5% percentile": 0.593758}, "Prevalence": {"value": 0.101871, "mean": 0.10202, "median": 0.101871, "std": 0.009771, "2.5% percentile": 0.08316, "97.5% percentile": 0.121622}, "Accuracy": {"value": 0.911642, "mean": 0.911546, "median": 0.911642, "std": 0.009174, "2.5% percentile": 0.892931, "97.5% percentile": 0.929314}, "Precision0": {"value": 0.914803, "mean": 0.9147, "median": 0.914803, "std": 0.009098, "2.5% percentile": 0.896589, "97.5% percentile": 0.932059}, "Precision1": {"value": 0.782609, "mean": 0.783022, "median": 0.789474, "std": 0.088081, "2.5% percentile": 0.6, "97.5% percentile": 0.947368}, "Recall0": {"value": 0.994213, "mean": 0.994211, "median": 0.99424, "std": 0.00258, "2.5% percentile": 0.988453, "97.5% percentile": 0.998841}, "Recall1": {"value": 0.183673, "mean": 0.183904, "median": 0.182692, "std": 0.039063, "2.5% percentile": 0.111111, "97.5% percentile": 0.263636}, "False Negative Rate": {"value": 0.816327, "mean": 0.816096, "median": 0.817308, "std": 0.039063, "2.5% percentile": 0.736364, "97.5% percentile": 0.888889}, "False Positive Rate": {"value": 0.005787, "mean": 0.005789, "median": 0.00576, "std": 0.00258, "2.5% percentile": 0.001159, "97.5% percentile": 0.011547}, "Average predicted risk": {"value": 0.078262, "mean": 0.078336, "median": 0.078238, "std": 0.004369, "2.5% percentile": 0.069879, "97.5% percentile": 0.087044}, "Average observed risk": {"value": 0.101871, "mean": 0.10202, "median": 0.101871, "std": 0.009771, "2.5% percentile": 0.08316, "97.5% percentile": 0.121622}, "Difference in average predicted and observed risk": {"value": -0.023609000000000005, "mean": -0.023684, "median": -0.023653, "std": 0.008393, "2.5% percentile": -0.040311, "97.5% percentile": -0.007543}}, "binaryIns": {"Private": {"AUC of ROC": {"value": 0.884705, "mean": 0.884764, "median": 0.886462, "std": 0.030408, "2.5% percentile": 0.819548, "97.5% percentile": 0.940083}, "AUC of PRC": {"value": 0.453753, "mean": 0.470693, "median": 0.464789, "std": 0.100513, "2.5% percentile": 0.284607, "97.5% percentile": 0.678186}, "min(+P, Se)": {"value": 0.518519, "mean": 0.536457, "median": 0.538462, "std": 0.079124, "2.5% percentile": 0.375, "97.5% percentile": 0.685714}, "Prevalence": {"value": 0.101504, "mean": 0.101567, "median": 0.101504, "std": 0.018308, "2.5% percentile": 0.067669, "97.5% percentile": 0.139098}, "Accuracy": {"value": 0.906015, "mean": 0.905945, "median": 0.906015, "std": 0.017746, "2.5% percentile": 0.868421, "97.5% percentile": 0.93985}, "Precision0": {"value": 0.908397, "mean": 0.908321, "median": 0.908745, "std": 0.017645, "2.5% percentile": 0.872577, "97.5% percentile": 0.939883}, "Precision1": {"value": 0.75, "mean": null, "median": null, "std": null, "2.5% percentile": null, "97.5% percentile": null}, "Recall0": {"value": 0.995816, "mean": 0.995823, "median": 0.995851, "std": 0.004217, "2.5% percentile": 0.987124, "97.5% percentile": 1.0}, "Recall1": {"value": 0.111111, "mean": 0.110898, "median": 0.105263, "std": 0.06175, "2.5% percentile": 0.0, "97.5% percentile": 0.241379}, "False Negative Rate": {"value": 0.888889, "mean": 0.889102, "median": 0.894737, "std": 0.06175, "2.5% percentile": 0.758621, "97.5% percentile": 1.0}, "False Positive Rate": {"value": 0.004184, "mean": 0.004177, "median": 0.004149, "std": 0.004217, "2.5% percentile": 0.0, "97.5% percentile": 0.012876}, "Average predicted risk": {"value": 0.073391, "mean": 0.073325, "median": 0.073168, "std": 0.007997, "2.5% percentile": 0.058324, "97.5% percentile": 0.089567}, "Average observed risk": {"value": 0.101504, "mean": 0.101567, "median": 0.101504, "std": 0.018308, "2.5% percentile": 0.067669, "97.5% percentile": 0.139098}, "Difference in average predicted and observed risk": {"value": -0.028113, "mean": -0.028243, "median": -0.02795, "std": 0.0159, "2.5% percentile": -0.060535, "97.5% percentile": 0.002012}}, "Public": {"AUC of ROC": {"value": 0.856132, "mean": 0.85646, "median": 0.857585, "std": 0.022, "2.5% percentile": 0.810829, "97.5% percentile": 0.896801}, "AUC of PRC": {"value": 0.476299, "mean": 0.479465, "median": 0.479706, "std": 0.065379, "2.5% percentile": 0.348705, "97.5% percentile": 0.606102}, "min(+P, Se)": {"value": 0.485294, "mean": 0.483286, "median": 0.484375, "std": 0.053772, "2.5% percentile": 0.376434, "97.5% percentile": 0.585375}, "Prevalence": {"value": 0.102041, "mean": 0.102036, "median": 0.102041, "std": 0.011947, "2.5% percentile": 0.078493, "97.5% percentile": 0.127159}, "Accuracy": {"value": 0.910518, "mean": 0.910591, "median": 0.910518, "std": 0.011229, "2.5% percentile": 0.88854, "97.5% percentile": 0.932496}, "Precision0": {"value": 0.914654, "mean": 0.914734, "median": 0.914791, "std": 0.011117, "2.5% percentile": 0.892283, "97.5% percentile": 0.935795}, "Precision1": {"value": 0.75, "mean": 0.750345, "median": 0.75, "std": 0.110667, "2.5% percentile": 0.526253, "97.5% percentile": 0.944444}, "Recall0": {"value": 0.993007, "mean": 0.99299, "median": 0.993043, "std": 0.003475, "2.5% percentile": 0.985841, "97.5% percentile": 0.998279}, "Recall1": {"value": 0.184615, "mean": 0.18539, "median": 0.183333, "std": 0.047932, "2.5% percentile": 0.09589, "97.5% percentile": 0.283333}, "False Negative Rate": {"value": 0.815385, "mean": 0.81461, "median": 0.816667, "std": 0.047932, "2.5% percentile": 0.716667, "97.5% percentile": 0.90411}, "False Positive Rate": {"value": 0.006993, "mean": 0.00701, "median": 0.006957, "std": 0.003475, "2.5% percentile": 0.001721, "97.5% percentile": 0.014159}, "Average predicted risk": {"value": 0.078758, "mean": 0.078751, "median": 0.078672, "std": 0.005146, "2.5% percentile": 0.069025, "97.5% percentile": 0.089078}, "Average observed risk": {"value": 0.102041, "mean": 0.102036, "median": 0.102041, "std": 0.011947, "2.5% percentile": 0.078493, "97.5% percentile": 0.127159}, "Difference in average predicted and observed risk": {"value": -0.023283000000000012, "mean": -0.023285, "median": -0.023138, "std": 0.010416, "2.5% percentile": -0.044095, "97.5% percentile": -0.003696}}, "Selfpay": {"AUC of ROC": {"value": 0.968553, "mean": null, "median": null, "std": null, "2.5% percentile": null, "97.5% percentile": null}, "AUC of PRC": {"value": 0.849512, "mean": null, "median": null, "std": null, "2.5% percentile": null, "97.5% percentile": null}, "min(+P, Se)": {"value": 0.714286, "mean": 0.758788, "median": 0.75, "std": 0.163429, "2.5% percentile": 0.4, "97.5% percentile": 1.0}, "Prevalence": {"value": 0.101695, "mean": 0.100992, "median": 0.101695, "std": 0.038898, "2.5% percentile": 0.033898, "97.5% percentile": 0.186441}, "Accuracy": {"value": 0.949153, "mean": 0.949419, "median": 0.949153, "std": 0.02856, "2.5% percentile": 0.881356, "97.5% percentile": 1.0}, "Precision0": {"value": 0.946429, "mean": 0.946741, "median": 0.947368, "std": 0.03003, "2.5% percentile": 0.87931, "97.5% percentile": 1.0}, "Precision1": {"value": 1.0, "mean": null, "median": null, "std": null, "2.5% percentile": null, "97.5% percentile": null}, "Recall0": {"value": 1.0, "mean": 1.0, "median": 1.0, "std": 0.0, "2.5% percentile": 1.0, "97.5% percentile": 1.0}, "Recall1": {"value": 0.5, "mean": null, "median": null, "std": null, "2.5% percentile": null, "97.5% percentile": null}, "False Negative Rate": {"value": 0.5, "mean": null, "median": null, "std": null, "2.5% percentile": null, "97.5% percentile": null}, "False Positive Rate": {"value": 0.0, "mean": 0.0, "median": 0.0, "std": 0.0, "2.5% percentile": 0.0, "97.5% percentile": 0.0}, "Average predicted risk": {"value": 0.094861, "mean": 0.09462, "median": 0.09324, "std": 0.023523, "2.5% percentile": 0.052251, "97.5% percentile": 0.143178}, "Average observed risk": {"value": 0.101695, "mean": 0.100992, "median": 0.101695, "std": 0.038898, "2.5% percentile": 0.033898, "97.5% percentile": 0.186441}, "Difference in average predicted and observed risk": {"value": -0.006833999999999993, "mean": -0.006371, "median": -0.004896, "std": 0.026008, "2.5% percentile": -0.061492, "97.5% percentile": 0.040707}}}, "Insurance": {"Other": {"AUC of ROC": {"value": 0.968553, "mean": null, "median": null, "std": null, "2.5% percentile": null, "97.5% percentile": null}, "AUC of PRC": {"value": 0.849512, "mean": null, "median": null, "std": null, "2.5% percentile": null, "97.5% percentile": null}, "min(+P, Se)": {"value": 0.714286, "mean": 0.761734, "median": 0.777778, "std": 0.1628, "2.5% percentile": 0.4, "97.5% percentile": 1.0}, "Prevalence": {"value": 0.101695, "mean": 0.102098, "median": 0.101695, "std": 0.039193, "2.5% percentile": 0.033898, "97.5% percentile": 0.186441}, "Accuracy": {"value": 0.949153, "mean": 0.948983, "median": 0.949153, "std": 0.028904, "2.5% percentile": 0.881356, "97.5% percentile": 1.0}, "Precision0": {"value": 0.946429, "mean": 0.946245, "median": 0.947368, "std": 0.030412, "2.5% percentile": 0.877193, "97.5% percentile": 1.0}, "Precision1": {"value": 1.0, "mean": null, "median": null, "std": null, "2.5% percentile": null, "97.5% percentile": null}, "Recall0": {"value": 1.0, "mean": 1.0, "median": 1.0, "std": 0.0, "2.5% percentile": 1.0, "97.5% percentile": 1.0}, "Recall1": {"value": 0.5, "mean": null, "median": null, "std": null, "2.5% percentile": null, "97.5% percentile": null}, "False Negative Rate": {"value": 0.5, "mean": null, "median": null, "std": null, "2.5% percentile": null, "97.5% percentile": null}, "False Positive Rate": {"value": 0.0, "mean": 0.0, "median": 0.0, "std": 0.0, "2.5% percentile": 0.0, "97.5% percentile": 0.0}, "Average predicted risk": {"value": 0.094861, "mean": 0.09526, "median": 0.093497, "std": 0.023583, "2.5% percentile": 0.053425, "97.5% percentile": 0.144238}, "Average observed risk": {"value": 0.101695, "mean": 0.102098, "median": 0.101695, "std": 0.039193, "2.5% percentile": 0.033898, "97.5% percentile": 0.186441}, "Difference in average predicted and observed risk": {"value": -0.006833999999999993, "mean": -0.006839, "median": -0.00555, "std": 0.026355, "2.5% percentile": -0.06138, "97.5% percentile": 0.041707}}, "Medicare": {"AUC of ROC": {"value": 0.87152, "mean": 0.871233, "median": 0.872306, "std": 0.024968, "2.5% percentile": 0.819223, "97.5% percentile": 0.917089}, "AUC of PRC": {"value": 0.534924, "mean": 0.535966, "median": 0.538708, "std": 0.075541, "2.5% percentile": 0.380663, "97.5% percentile": 0.677394}, "min(+P, Se)": {"value": 0.5, "mean": 0.513565, "median": 0.512821, "std": 0.062693, "2.5% percentile": 0.391304, "97.5% percentile": 0.634615}, "Prevalence": {"value": 0.100209, "mean": 0.100067, "median": 0.100209, "std": 0.013528, "2.5% percentile": 0.075157, "97.5% percentile": 0.127349}, "Accuracy": {"value": 0.920668, "mean": 0.920786, "median": 0.920668, "std": 0.012197, "2.5% percentile": 0.895616, "97.5% percentile": 0.943633}, "Precision0": {"value": 0.922581, "mean": 0.922701, "median": 0.922912, "std": 0.012236, "2.5% percentile": 0.897871, "97.5% percentile": 0.946004}, "Precision1": {"value": 0.857143, "mean": 0.856692, "median": 0.866667, "std": 0.097161, "2.5% percentile": 0.642857, "97.5% percentile": 1.0}, "Recall0": {"value": 0.99536, "mean": 0.995366, "median": 0.995381, "std": 0.003218, "2.5% percentile": 0.98829, "97.5% percentile": 1.0}, "Recall1": {"value": 0.25, "mean": 0.250016, "median": 0.25, "std": 0.063368, "2.5% percentile": 0.130435, "97.5% percentile": 0.377793}, "False Negative Rate": {"value": 0.75, "mean": 0.749984, "median": 0.75, "std": 0.063368, "2.5% percentile": 0.622207, "97.5% percentile": 0.869565}, "False Positive Rate": {"value": 0.00464, "mean": 0.004634, "median": 0.004619, "std": 0.003218, "2.5% percentile": 0.0, "97.5% percentile": 0.01171}, "Average predicted risk": {"value": 0.080719, "mean": 0.080683, "median": 0.080544, "std": 0.00615, "2.5% percentile": 0.069185, "97.5% percentile": 0.093219}, "Average observed risk": {"value": 0.100209, "mean": 0.100067, "median": 0.100209, "std": 0.013528, "2.5% percentile": 0.075157, "97.5% percentile": 0.127349}, "Difference in average predicted and observed risk": {"value": -0.019490000000000007, "mean": -0.019384, "median": -0.019092, "std": 0.011521, "2.5% percentile": -0.042736, "97.5% percentile": 0.002435}}, "Medicaid": {"AUC of ROC": {"value": 0.813517, "mean": 0.814535, "median": 0.81649, "std": 0.046383, "2.5% percentile": 0.717066, "97.5% percentile": 0.900299}, "AUC of PRC": {"value": 0.30839, "mean": 0.327291, "median": 0.316635, "std": 0.103046, "2.5% percentile": 0.156272, "97.5% percentile": 0.56707}, "min(+P, Se)": {"value": 0.411765, "mean": 0.412847, "median": 0.411765, "std": 0.098959, "2.5% percentile": 0.222222, "97.5% percentile": 0.608696}, "Prevalence": {"value": 0.107595, "mean": 0.107763, "median": 0.107595, "std": 0.024549, "2.5% percentile": 0.063291, "97.5% percentile": 0.158228}, "Accuracy": {"value": 0.879747, "mean": 0.879558, "median": 0.879747, "std": 0.025965, "2.5% percentile": 0.829114, "97.5% percentile": 0.93038}, "Precision0": {"value": 0.891026, "mean": 0.890848, "median": 0.891026, "std": 0.024871, "2.5% percentile": 0.839744, "97.5% percentile": 0.936306}, "Precision1": {"value": 0.0, "mean": null, "median": null, "std": null, "2.5% percentile": null, "97.5% percentile": null}, "Recall0": {"value": 0.985816, "mean": 0.985784, "median": 0.985915, "std": 0.010012, "2.5% percentile": 0.964029, "97.5% percentile": 1.0}, "Recall1": {"value": 0.0, "mean": 0.0, "median": 0.0, "std": 0.0, "2.5% percentile": 0.0, "97.5% percentile": 0.0}, "False Negative Rate": {"value": 1.0, "mean": 1.0, "median": 1.0, "std": 0.0, "2.5% percentile": 1.0, "97.5% percentile": 1.0}, "False Positive Rate": {"value": 0.014184, "mean": 0.014216, "median": 0.014085, "std": 0.010012, "2.5% percentile": 0.0, "97.5% percentile": 0.035971}, "Average predicted risk": {"value": 0.072815, "mean": 0.072973, "median": 0.072692, "std": 0.009034, "2.5% percentile": 0.056226, "97.5% percentile": 0.091568}, "Average observed risk": {"value": 0.107595, "mean": 0.107763, "median": 0.107595, "std": 0.024549, "2.5% percentile": 0.063291, "97.5% percentile": 0.158228}, "Difference in average predicted and observed risk": {"value": -0.03477999999999999, "mean": -0.03479, "median": -0.034319, "std": 0.023188, "2.5% percentile": -0.081603, "97.5% percentile": 0.009612}}, "Private": {"AUC of ROC": {"value": 0.884705, "mean": 0.884279, "median": 0.885897, "std": 0.030842, "2.5% percentile": 0.817708, "97.5% percentile": 0.938946}, "AUC of PRC": {"value": 0.453753, "mean": 0.469795, "median": 0.465681, "std": 0.101246, "2.5% percentile": 0.284573, "97.5% percentile": 0.675846}, "min(+P, Se)": {"value": 0.518519, "mean": 0.536952, "median": 0.538462, "std": 0.080325, "2.5% percentile": 0.375, "97.5% percentile": 0.6875}, "Prevalence": {"value": 0.101504, "mean": 0.101714, "median": 0.101504, "std": 0.018585, "2.5% percentile": 0.067669, "97.5% percentile": 0.139098}, "Accuracy": {"value": 0.906015, "mean": 0.905716, "median": 0.906015, "std": 0.01793, "2.5% percentile": 0.868421, "97.5% percentile": 0.93985}, "Precision0": {"value": 0.908397, "mean": 0.90811, "median": 0.908745, "std": 0.017871, "2.5% percentile": 0.871212, "97.5% percentile": 0.942308}, "Precision1": {"value": 0.75, "mean": null, "median": null, "std": null, "2.5% percentile": null, "97.5% percentile": null}, "Recall0": {"value": 0.995816, "mean": 0.995803, "median": 0.995851, "std": 0.004129, "2.5% percentile": 0.987179, "97.5% percentile": 1.0}, "Recall1": {"value": 0.111111, "mean": 0.110035, "median": 0.105263, "std": 0.061252, "2.5% percentile": 0.0, "97.5% percentile": 0.24}, "False Negative Rate": {"value": 0.888889, "mean": 0.889965, "median": 0.894737, "std": 0.061252, "2.5% percentile": 0.76, "97.5% percentile": 1.0}, "False Positive Rate": {"value": 0.004184, "mean": 0.004197, "median": 0.004149, "std": 0.004129, "2.5% percentile": 0.0, "97.5% percentile": 0.012821}, "Average predicted risk": {"value": 0.073391, "mean": 0.073313, "median": 0.073054, "std": 0.008087, "2.5% percentile": 0.058198, "97.5% percentile": 0.089643}, "Average observed risk": {"value": 0.101504, "mean": 0.101714, "median": 0.101504, "std": 0.018585, "2.5% percentile": 0.067669, "97.5% percentile": 0.139098}, "Difference in average predicted and observed risk": {"value": -0.028113, "mean": -0.028402, "median": -0.028075, "std": 0.016081, "2.5% percentile": -0.061259, "97.5% percentile": 0.001625}}}, "Gender": {"F": {"AUC of ROC": {"value": 0.877897, "mean": 0.87784, "median": 0.879028, "std": 0.024381, "2.5% percentile": 0.826575, "97.5% percentile": 0.921914}, "AUC of PRC": {"value": 0.558862, "mean": 0.55927, "median": 0.561808, "std": 0.073105, "2.5% percentile": 0.409347, "97.5% percentile": 0.69758}, "min(+P, Se)": {"value": 0.568627, "mean": 0.570068, "median": 0.571429, "std": 0.058517, "2.5% percentile": 0.45098, "97.5% percentile": 0.678571}, "Prevalence": {"value": 0.126551, "mean": 0.126517, "median": 0.126551, "std": 0.016715, "2.5% percentile": 0.094293, "97.5% percentile": 0.158809}, "Accuracy": {"value": 0.8933, "mean": 0.893189, "median": 0.8933, "std": 0.015452, "2.5% percentile": 0.863524, "97.5% percentile": 0.923077}, "Precision0": {"value": 0.895141, "mean": 0.895099, "median": 0.895408, "std": 0.015562, "2.5% percentile": 0.864103, "97.5% percentile": 0.924051}, "Precision1": {"value": 0.833333, "mean": 0.831266, "median": 0.833333, "std": 0.113208, "2.5% percentile": 0.583333, "97.5% percentile": 1.0}, "Recall0": {"value": 0.994318, "mean": 0.994235, "median": 0.99435, "std": 0.004082, "2.5% percentile": 0.985548, "97.5% percentile": 1.0}, "Recall1": {"value": 0.196078, "mean": 0.195506, "median": 0.192982, "std": 0.055587, "2.5% percentile": 0.092593, "97.5% percentile": 0.309545}, "False Negative Rate": {"value": 0.803922, "mean": 0.804494, "median": 0.807018, "std": 0.055587, "2.5% percentile": 0.690455, "97.5% percentile": 0.907407}, "False Positive Rate": {"value": 0.005682, "mean": 0.005765, "median": 0.00565, "std": 0.004082, "2.5% percentile": 0.0, "97.5% percentile": 0.014452}, "Average predicted risk": {"value": 0.092346, "mean": 0.092307, "median": 0.092208, "std": 0.007519, "2.5% percentile": 0.078028, "97.5% percentile": 0.107698}, "Average observed risk": {"value": 0.126551, "mean": 0.126517, "median": 0.126551, "std": 0.016715, "2.5% percentile": 0.094293, "97.5% percentile": 0.158809}, "Difference in average predicted and observed risk": {"value": -0.034205, "mean": -0.03421, "median": -0.034044, "std": 0.014111, "2.5% percentile": -0.062307, "97.5% percentile": -0.007316}}, "M": {"AUC of ROC": {"value": 0.862035, "mean": 0.862633, "median": 0.863914, "std": 0.024376, "2.5% percentile": 0.81177, "97.5% percentile": 0.907708}, "AUC of PRC": {"value": 0.415327, "mean": 0.427376, "median": 0.425999, "std": 0.078803, "2.5% percentile": 0.278644, "97.5% percentile": 0.586062}, "min(+P, Se)": {"value": 0.431373, "mean": 0.450735, "median": 0.452381, "std": 0.064248, "2.5% percentile": 0.321412, "97.5% percentile": 0.575}, "Prevalence": {"value": 0.084079, "mean": 0.084113, "median": 0.084079, "std": 0.011818, "2.5% percentile": 0.062567, "97.5% percentile": 0.109123}, "Accuracy": {"value": 0.924866, "mean": 0.924916, "median": 0.924866, "std": 0.011155, "2.5% percentile": 0.90161, "97.5% percentile": 0.946333}, "Precision0": {"value": 0.928832, "mean": 0.928851, "median": 0.928962, "std": 0.011059, "2.5% percentile": 0.906593, "97.5% percentile": 0.949367}, "Precision1": {"value": 0.727273, "mean": null, "median": null, "std": null, "2.5% percentile": null, "97.5% percentile": null}, "Recall0": {"value": 0.994141, "mean": 0.994176, "median": 0.994175, "std": 0.00336, "2.5% percentile": 0.986434, "97.5% percentile": 1.0}, "Recall1": {"value": 0.170213, "mean": 0.170762, "median": 0.169811, "std": 0.056112, "2.5% percentile": 0.068182, "97.5% percentile": 0.285714}, "False Negative Rate": {"value": 0.829787, "mean": 0.829238, "median": 0.830189, "std": 0.056112, "2.5% percentile": 0.714286, "97.5% percentile": 0.931818}, "False Positive Rate": {"value": 0.005859, "mean": 0.005824, "median": 0.005825, "std": 0.003359, "2.5% percentile": 0.0, "97.5% percentile": 0.013566}, "Average predicted risk": {"value": 0.068107, "mean": 0.068133, "median": 0.068012, "std": 0.005105, "2.5% percentile": 0.058432, "97.5% percentile": 0.078512}, "Average observed risk": {"value": 0.084079, "mean": 0.084113, "median": 0.084079, "std": 0.011818, "2.5% percentile": 0.062567, "97.5% percentile": 0.109123}, "Difference in average predicted and observed risk": {"value": -0.015972, "mean": -0.01598, "median": -0.015858, "std": 0.010531, "2.5% percentile": -0.037093, "97.5% percentile": 0.004236}}}, "Ethnicity": {"OTHER": {"AUC of ROC": {"value": 0.827586, "mean": 0.827873, "median": 0.832906, "std": 0.06273, "2.5% percentile": 0.692976, "97.5% percentile": 0.935783}, "AUC of PRC": {"value": 0.460162, "mean": 0.462856, "median": 0.466986, "std": 0.138062, "2.5% percentile": 0.174555, "97.5% percentile": 0.720374}, "min(+P, Se)": {"value": 0.4, "mean": 0.449994, "median": 0.454545, "std": 0.110894, "2.5% percentile": 0.230769, "97.5% percentile": 0.666667}, "Prevalence": {"value": 0.100775, "mean": 0.101231, "median": 0.100775, "std": 0.026352, "2.5% percentile": 0.054264, "97.5% percentile": 0.155039}, "Accuracy": {"value": 0.906977, "mean": 0.906719, "median": 0.906977, "std": 0.025333, "2.5% percentile": 0.852713, "97.5% percentile": 0.953488}, "Precision0": {"value": 0.912698, "mean": 0.912352, "median": 0.913386, "std": 0.024871, "2.5% percentile": 0.860465, "97.5% percentile": 0.96}, "Precision1": {"value": 0.666667, "mean": null, "median": null, "std": null, "2.5% percentile": null, "97.5% percentile": null}, "Recall0": {"value": 0.991379, "mean": 0.991454, "median": 0.991453, "std": 0.008531, "2.5% percentile": 0.973214, "97.5% percentile": 1.0}, "Recall1": {"value": 0.153846, "mean": 0.153788, "median": 0.142857, "std": 0.103487, "2.5% percentile": 0.0, "97.5% percentile": 0.375}, "False Negative Rate": {"value": 0.846154, "mean": 0.846212, "median": 0.857143, "std": 0.103487, "2.5% percentile": 0.625, "97.5% percentile": 1.0}, "False Positive Rate": {"value": 0.008621, "mean": 0.008546, "median": 0.008547, "std": 0.008531, "2.5% percentile": 0.0, "97.5% percentile": 0.026786}, "Average predicted risk": {"value": 0.075239, "mean": 0.075496, "median": 0.075012, "std": 0.011704, "2.5% percentile": 0.054101, "97.5% percentile": 0.099982}, "Average observed risk": {"value": 0.100775, "mean": 0.101231, "median": 0.100775, "std": 0.026352, "2.5% percentile": 0.054264, "97.5% percentile": 0.155039}, "Difference in average predicted and observed risk": {"value": -0.025536000000000003, "mean": -0.025735, "median": -0.024604, "std": 0.023328, "2.5% percentile": -0.073694, "97.5% percentile": 0.017836}}, "ASIAN": {"AUC of ROC": {"value": 0.878803, "mean": 0.879196, "median": 0.88141, "std": 0.040776, "2.5% percentile": 0.792315, "97.5% percentile": 0.952174}, "AUC of PRC": {"value": 0.533994, "mean": 0.55776, "median": 0.55342, "std": 0.135059, "2.5% percentile": 0.298786, "97.5% percentile": 0.809338}, "min(+P, Se)": {"value": 0.588235, "mean": 0.573236, "median": 0.578947, "std": 0.101862, "2.5% percentile": 0.36, "97.5% percentile": 0.764706}, "Prevalence": {"value": 0.12782, "mean": 0.12785, "median": 0.12782, "std": 0.02911, "2.5% percentile": 0.075188, "97.5% percentile": 0.18797}, "Accuracy": {"value": 0.894737, "mean": 0.894783, "median": 0.894737, "std": 0.026733, "2.5% percentile": 0.842105, "97.5% percentile": 0.947368}, "Precision0": {"value": 0.898438, "mean": 0.898404, "median": 0.899225, "std": 0.026762, "2.5% percentile": 0.84252, "97.5% percentile": 0.946154}, "Precision1": {"value": 0.8, "mean": null, "median": null, "std": null, "2.5% percentile": null, "97.5% percentile": null}, "Recall0": {"value": 0.991379, "mean": 0.991466, "median": 0.991525, "std": 0.008482, "2.5% percentile": 0.973214, "97.5% percentile": 1.0}, "Recall1": {"value": 0.235294, "mean": 0.234999, "median": 0.230769, "std": 0.106128, "2.5% percentile": 0.052632, "97.5% percentile": 0.454545}, "False Negative Rate": {"value": 0.764706, "mean": 0.765001, "median": 0.769231, "std": 0.106128, "2.5% percentile": 0.545455, "97.5% percentile": 0.947368}, "False Positive Rate": {"value": 0.008621, "mean": 0.008534, "median": 0.008475, "std": 0.008482, "2.5% percentile": 0.0, "97.5% percentile": 0.026786}, "Average predicted risk": {"value": 0.099139, "mean": 0.099098, "median": 0.098821, "std": 0.013957, "2.5% percentile": 0.073163, "97.5% percentile": 0.127483}, "Average observed risk": {"value": 0.12782, "mean": 0.12785, "median": 0.12782, "std": 0.02911, "2.5% percentile": 0.075188, "97.5% percentile": 0.18797}, "Difference in average predicted and observed risk": {"value": -0.028680999999999984, "mean": -0.028752, "median": -0.027632, "std": 0.024095, "2.5% percentile": -0.077627, "97.5% percentile": 0.015835}}, "BLACK": {"AUC of ROC": {"value": 0.67619, "mean": null, "median": null, "std": null, "2.5% percentile": null, "97.5% percentile": null}, "AUC of PRC": {"value": 0.133792, "mean": null, "median": null, "std": null, "2.5% percentile": null, "97.5% percentile": null}, "min(+P, Se)": {"value": 0.2, "mean": 0.248144, "median": 0.214286, "std": 0.150526, "2.5% percentile": 0.047619, "97.5% percentile": 0.6}, "Prevalence": {"value": 0.073529, "mean": 0.073526, "median": 0.073529, "std": 0.031861, "2.5% percentile": 0.014706, "97.5% percentile": 0.147059}, "Accuracy": {"value": 0.926471, "mean": 0.926474, "median": 0.926471, "std": 0.031861, "2.5% percentile": 0.852941, "97.5% percentile": 0.985294}, "Precision0": {"value": 0.926471, "mean": 0.926474, "median": 0.926471, "std": 0.031861, "2.5% percentile": 0.852941, "97.5% percentile": 0.985294}, "Precision1": {"value": null, "mean": null, "median": null, "std": null, "2.5% percentile": null, "97.5% percentile": null}, "Recall0": {"value": 1.0, "mean": 1.0, "median": 1.0, "std": 0.0, "2.5% percentile": 1.0, "97.5% percentile": 1.0}, "Recall1": {"value": 0.0, "mean": null, "median": null, "std": null, "2.5% percentile": null, "97.5% percentile": null}, "False Negative Rate": {"value": 1.0, "mean": null, "median": null, "std": null, "2.5% percentile": null, "97.5% percentile": null}, "False Positive Rate": {"value": 0.0, "mean": 0.0, "median": 0.0, "std": 0.0, "2.5% percentile": 0.0, "97.5% percentile": 0.0}, "Average predicted risk": {"value": 0.069068, "mean": 0.06912, "median": 0.068448, "std": 0.012346, "2.5% percentile": 0.047267, "97.5% percentile": 0.094688}, "Average observed risk": {"value": 0.073529, "mean": 0.073526, "median": 0.073529, "std": 0.031861, "2.5% percentile": 0.014706, "97.5% percentile": 0.147059}, "Difference in average predicted and observed risk": {"value": -0.004460999999999993, "mean": -0.004407, "median": -0.00271, "std": 0.032028, "2.5% percentile": -0.071941, "97.5% percentile": 0.052435}}, "HISPANIC": {"AUC of ROC": {"value": 0.892157, "mean": 0.892045, "median": 0.896206, "std": 0.041873, "2.5% percentile": 0.798145, "97.5% percentile": 0.960598}, "AUC of PRC": {"value": 0.564377, "mean": 0.569048, "median": 0.573228, "std": 0.124777, "2.5% percentile": 0.313766, "97.5% percentile": 0.79785}, "min(+P, Se)": {"value": 0.583333, "mean": 0.595947, "median": 0.6, "std": 0.093841, "2.5% percentile": 0.4, "97.5% percentile": 0.772727}, "Prevalence": {"value": 0.116883, "mean": 0.116701, "median": 0.116883, "std": 0.025928, "2.5% percentile": 0.071429, "97.5% percentile": 0.168831}, "Accuracy": {"value": 0.909091, "mean": 0.909235, "median": 0.909091, "std": 0.023317, "2.5% percentile": 0.863636, "97.5% percentile": 0.954545}, "Precision0": {"value": 0.912162, "mean": 0.912339, "median": 0.912752, "std": 0.023319, "2.5% percentile": 0.864865, "97.5% percentile": 0.953333}, "Precision1": {"value": 0.833333, "mean": null, "median": null, "std": null, "2.5% percentile": null, "97.5% percentile": null}, "Recall0": {"value": 0.992647, "mean": 0.992614, "median": 0.992754, "std": 0.007368, "2.5% percentile": 0.977099, "97.5% percentile": 1.0}, "Recall1": {"value": 0.277778, "mean": 0.27812, "median": 0.272727, "std": 0.109381, "2.5% percentile": 0.071429, "97.5% percentile": 0.5}, "False Negative Rate": {"value": 0.722222, "mean": 0.72188, "median": 0.727273, "std": 0.109381, "2.5% percentile": 0.5, "97.5% percentile": 0.928571}, "False Positive Rate": {"value": 0.007353, "mean": 0.007386, "median": 0.007246, "std": 0.007368, "2.5% percentile": 0.0, "97.5% percentile": 0.022901}, "Average predicted risk": {"value": 0.091476, "mean": 0.09147, "median": 0.091056, "std": 0.012067, "2.5% percentile": 0.068746, "97.5% percentile": 0.116383}, "Average observed risk": {"value": 0.116883, "mean": 0.116701, "median": 0.116883, "std": 0.025928, "2.5% percentile": 0.071429, "97.5% percentile": 0.168831}, "Difference in average predicted and observed risk": {"value": -0.025407, "mean": -0.025231, "median": -0.024463, "std": 0.021489, "2.5% percentile": -0.068958, "97.5% percentile": 0.015572}}, "WHITE": {"AUC of ROC": {"value": 0.895047, "mean": 0.895015, "median": 0.896187, "std": 0.021204, "2.5% percentile": 0.849751, "97.5% percentile": 0.933591}, "AUC of PRC": {"value": 0.518045, "mean": 0.520701, "median": 0.523356, "std": 0.078854, "2.5% percentile": 0.360387, "97.5% percentile": 0.666121}, "min(+P, Se)": {"value": 0.511111, "mean": 0.510764, "median": 0.511111, "std": 0.0656, "2.5% percentile": 0.382353, "97.5% percentile": 0.636364}, "Prevalence": {"value": 0.094142, "mean": 0.094144, "median": 0.094142, "std": 0.013336, "2.5% percentile": 0.069038, "97.5% percentile": 0.121339}, "Accuracy": {"value": 0.916318, "mean": 0.916372, "median": 0.916318, "std": 0.012571, "2.5% percentile": 0.891213, "97.5% percentile": 0.939331}, "Precision0": {"value": 0.918977, "mean": 0.918993, "median": 0.919149, "std": 0.012552, "2.5% percentile": 0.893617, "97.5% percentile": 0.942553}, "Precision1": {"value": 0.777778, "mean": null, "median": null, "std": null, "2.5% percentile": null, "97.5% percentile": null}, "Recall0": {"value": 0.995381, "mean": 0.995427, "median": 0.995413, "std": 0.003226, "2.5% percentile": 0.988372, "97.5% percentile": 1.0}, "Recall1": {"value": 0.155556, "mean": 0.155656, "median": 0.152542, "std": 0.054604, "2.5% percentile": 0.057143, "97.5% percentile": 0.269231}, "False Negative Rate": {"value": 0.844444, "mean": 0.844344, "median": 0.847458, "std": 0.054604, "2.5% percentile": 0.730769, "97.5% percentile": 0.942857}, "False Positive Rate": {"value": 0.004619, "mean": 0.004573, "median": 0.004587, "std": 0.003226, "2.5% percentile": 0.0, "97.5% percentile": 0.011628}, "Average predicted risk": {"value": 0.070319, "mean": 0.070263, "median": 0.070124, "std": 0.005679, "2.5% percentile": 0.059598, "97.5% percentile": 0.081794}, "Average observed risk": {"value": 0.094142, "mean": 0.094144, "median": 0.094142, "std": 0.013336, "2.5% percentile": 0.069038, "97.5% percentile": 0.121339}, "Difference in average predicted and observed risk": {"value": -0.023822999999999997, "mean": -0.023882, "median": -0.023516, "std": 0.011457, "2.5% percentile": -0.047124, "97.5% percentile": -0.002085}}}}