{"n_iters": 10000, "Overall": {"AUC of ROC": {"value": 0.858883, "mean": 0.858946, "median": 0.858934, "std": 0.005774, "2.5% percentile": 0.847569, "97.5% percentile": 0.870093}, "AUC of PRC": {"value": 0.749499, "mean": 0.749476, "median": 0.74943, "std": 0.011772, "2.5% percentile": 0.726307, "97.5% percentile": 0.772653}, "min(+P, Se)": {"value": 0.69395, "mean": 0.691386, "median": 0.691482, "std": 0.010257, "2.5% percentile": 0.670959, "97.5% percentile": 0.71108}, "Prevalence": {"value": 0.329271, "mean": 0.329239, "median": 0.329271, "std": 0.007166, "2.5% percentile": 0.31521, "97.5% percentile": 0.343333}, "Accuracy": {"value": 0.735411, "mean": 0.735418, "median": 0.735411, "std": 0.006799, "2.5% percentile": 0.722053, "97.5% percentile": 0.74877}, "Precision0": {"value": 0.723728, "mean": 0.723747, "median": 0.72381, "std": 0.007209, "2.5% percentile": 0.709426, "97.5% percentile": 0.737874}, "Precision1": {"value": 0.850254, "mean": 0.850173, "median": 0.850515, "std": 0.017828, "2.5% percentile": 0.813513, "97.5% percentile": 0.883955}, "Recall0": {"value": 0.979385, "mean": 0.979378, "median": 0.979464, "std": 0.002639, "2.5% percentile": 0.974053, "97.5% percentile": 0.984299}, "Recall1": {"value": 0.238434, "mean": 0.238403, "median": 0.238262, "std": 0.011386, "2.5% percentile": 0.216254, "97.5% percentile": 0.260962}, "False Negative Rate": {"value": 0.761566, "mean": 0.761597, "median": 0.761738, "std": 0.011386, "2.5% percentile": 0.739038, "97.5% percentile": 0.783746}, "False Positive Rate": {"value": 0.020615, "mean": 0.020622, "median": 0.020536, "std": 0.002639, "2.5% percentile": 0.015701, "97.5% percentile": 0.025947}, "Average predicted risk": {"value": 0.155582, "mean": 0.155561, "median": 0.15555, "std": 0.003127, "2.5% percentile": 0.149501, "97.5% percentile": 0.161704}, "Average observed risk": {"value": 0.329271, "mean": 0.329239, "median": 0.329271, "std": 0.007166, "2.5% percentile": 0.31521, "97.5% percentile": 0.343333}, "Difference in average predicted and observed risk": {"value": -0.17368899999999998, "mean": -0.173679, "median": -0.173588, "std": 0.006015, "2.5% percentile": -0.185589, "97.5% percentile": -0.162122}}, "binaryIns": {"Private": {"AUC of ROC": {"value": 0.887867, "mean": 0.887782, "median": 0.887834, "std": 0.00855, "2.5% percentile": 0.870618, "97.5% percentile": 0.904128}, "AUC of PRC": {"value": 0.837371, "mean": 0.83736, "median": 0.83779, "std": 0.014441, "2.5% percentile": 0.808112, "97.5% percentile": 0.864298}, "min(+P, Se)": {"value": 0.795764, "mean": 0.795749, "median": 0.795918, "std": 0.015554, "2.5% percentile": 0.764618, "97.5% percentile": 0.825348}, "Prevalence": {"value": 0.397476, "mean": 0.397608, "median": 0.397476, "std": 0.012348, "2.5% percentile": 0.373502, "97.5% percentile": 0.421451}, "Accuracy": {"value": 0.691483, "mean": 0.691405, "median": 0.691483, "std": 0.011735, "2.5% percentile": 0.668139, "97.5% percentile": 0.714196}, "Precision0": {"value": 0.665483, "mean": 0.665369, "median": 0.66548, "std": 0.012727, "2.5% percentile": 0.640481, "97.5% percentile": 0.689873}, "Precision1": {"value": 0.898305, "mean": 0.898538, "median": 0.899371, "std": 0.022746, "2.5% percentile": 0.852071, "97.5% percentile": 0.941176}, "Recall0": {"value": 0.981152, "mean": 0.981184, "median": 0.981308, "std": 0.004412, "2.5% percentile": 0.972132, "97.5% percentile": 0.989474}, "Recall1": {"value": 0.252381, "mean": 0.252391, "median": 0.252322, "std": 0.017273, "2.5% percentile": 0.219394, "97.5% percentile": 0.286823}, "False Negative Rate": {"value": 0.747619, "mean": 0.747609, "median": 0.747678, "std": 0.017273, "2.5% percentile": 0.713177, "97.5% percentile": 0.780606}, "False Positive Rate": {"value": 0.018848, "mean": 0.018816, "median": 0.018692, "std": 0.004412, "2.5% percentile": 0.010526, "97.5% percentile": 0.027868}, "Average predicted risk": {"value": 0.170612, "mean": 0.170645, "median": 0.170636, "std": 0.00549, "2.5% percentile": 0.160065, "97.5% percentile": 0.181631}, "Average observed risk": {"value": 0.397476, "mean": 0.397608, "median": 0.397476, "std": 0.012348, "2.5% percentile": 0.373502, "97.5% percentile": 0.421451}, "Difference in average predicted and observed risk": {"value": -0.22686399999999998, "mean": -0.226962, "median": -0.226862, "std": 0.010169, "2.5% percentile": -0.246655, "97.5% percentile": -0.207384}}, "Public": {"AUC of ROC": {"value": 0.837945, "mean": 0.83783, "median": 0.837908, "std": 0.008188, "2.5% percentile": 0.821499, "97.5% percentile": 0.85376}, "AUC of PRC": {"value": 0.677311, "mean": 0.677471, "median": 0.677493, "std": 0.018371, "2.5% percentile": 0.640532, "97.5% percentile": 0.713395}, "min(+P, Se)": {"value": 0.622047, "mean": 0.624623, "median": 0.624682, "std": 0.014992, "2.5% percentile": 0.595579, "97.5% percentile": 0.653847}, "Prevalence": {"value": 0.288855, "mean": 0.288884, "median": 0.288855, "std": 0.008849, "2.5% percentile": 0.271797, "97.5% percentile": 0.305923}, "Accuracy": {"value": 0.760045, "mean": 0.760099, "median": 0.760045, "std": 0.008267, "2.5% percentile": 0.743745, "97.5% percentile": 0.775976}, "Precision0": {"value": 0.755867, "mean": 0.755891, "median": 0.755906, "std": 0.008685, "2.5% percentile": 0.738739, "97.5% percentile": 0.772615}, "Precision1": {"value": 0.808612, "mean": 0.808948, "median": 0.809524, "std": 0.027012, "2.5% percentile": 0.754462, "97.5% percentile": 0.860696}, "Recall0": {"value": 0.978678, "mean": 0.978705, "median": 0.978791, "std": 0.003306, "2.5% percentile": 0.971883, "97.5% percentile": 0.984906}, "Recall1": {"value": 0.221785, "mean": 0.221969, "median": 0.221649, "std": 0.015143, "2.5% percentile": 0.192721, "97.5% percentile": 0.252091}, "False Negative Rate": {"value": 0.778215, "mean": 0.778031, "median": 0.778351, "std": 0.015143, "2.5% percentile": 0.747909, "97.5% percentile": 0.807279}, "False Positive Rate": {"value": 0.021322, "mean": 0.021295, "median": 0.021209, "std": 0.003306, "2.5% percentile": 0.015094, "97.5% percentile": 0.028117}, "Average predicted risk": {"value": 0.145336, "mean": 0.145364, "median": 0.14535, "std": 0.003797, "2.5% percentile": 0.137938, "97.5% percentile": 0.152983}, "Average observed risk": {"value": 0.288855, "mean": 0.288884, "median": 0.288855, "std": 0.008849, "2.5% percentile": 0.271797, "97.5% percentile": 0.305923}, "Difference in average predicted and observed risk": {"value": -0.14351899999999998, "mean": -0.14352, "median": -0.14349, "std": 0.007547, "2.5% percentile": -0.158318, "97.5% percentile": -0.128774}}, "Selfpay": {"AUC of ROC": {"value": 0.965261, "mean": 0.96537, "median": 0.969048, "std": 0.025644, "2.5% percentile": 0.905707, "97.5% percentile": 1.0}, "AUC of PRC": {"value": 0.909364, "mean": 0.906985, "median": 0.921248, "std": 0.078556, "2.5% percentile": 0.714998, "97.5% percentile": 1.0}, "min(+P, Se)": {"value": 0.857143, "mean": 0.870279, "median": 0.875, "std": 0.074587, "2.5% percentile": 0.7, "97.5% percentile": 1.0}, "Prevalence": {"value": 0.295455, "mean": 0.295782, "median": 0.295455, "std": 0.068799, "2.5% percentile": 0.159091, "97.5% percentile": 0.431818}, "Accuracy": {"value": 0.840909, "mean": 0.840175, "median": 0.840909, "std": 0.055478, "2.5% percentile": 0.727273, "97.5% percentile": 0.931818}, "Precision0": {"value": 0.833333, "mean": 0.832406, "median": 0.837838, "std": 0.062621, "2.5% percentile": 0.702703, "97.5% percentile": 0.944444}, "Precision1": {"value": 0.875, "mean": null, "median": null, "std": null, "2.5% percentile": null, "97.5% percentile": null}, "Recall0": {"value": 0.967742, "mean": 0.96787, "median": 0.96875, "std": 0.031567, "2.5% percentile": 0.896552, "97.5% percentile": 1.0}, "Recall1": {"value": 0.538462, "mean": 0.53612, "median": 0.538462, "std": 0.14259, "2.5% percentile": 0.25, "97.5% percentile": 0.8125}, "False Negative Rate": {"value": 0.461538, "mean": 0.46388, "median": 0.461538, "std": 0.14259, "2.5% percentile": 0.1875, "97.5% percentile": 0.75}, "False Positive Rate": {"value": 0.032258, "mean": 0.03213, "median": 0.03125, "std": 0.031567, "2.5% percentile": 0.0, "97.5% percentile": 0.103448}, "Average predicted risk": {"value": 0.228456, "mean": 0.228225, "median": 0.226811, "std": 0.045149, "2.5% percentile": 0.144665, "97.5% percentile": 0.320129}, "Average observed risk": {"value": 0.295455, "mean": 0.295782, "median": 0.295455, "std": 0.068799, "2.5% percentile": 0.159091, "97.5% percentile": 0.431818}, "Difference in average predicted and observed risk": {"value": -0.06699900000000003, "mean": -0.067556, "median": -0.066912, "std": 0.041443, "2.5% percentile": -0.152245, "97.5% percentile": 0.011667}}}, "Insurance": {"Government": {"AUC of ROC": {"value": 0.922523, "mean": 0.92256, "median": 0.92456, "std": 0.023414, "2.5% percentile": 0.87177, "97.5% percentile": 0.96304}, "AUC of PRC": {"value": 0.706153, "mean": 0.750646, "median": 0.722814, "std": 0.102499, "2.5% percentile": 0.58405, "97.5% percentile": 0.927345}, "min(+P, Se)": {"value": 0.702128, "mean": 0.720233, "median": 0.72093, "std": 0.059396, "2.5% percentile": 0.60368, "97.5% percentile": 0.836364}, "Prevalence": {"value": 0.291339, "mean": 0.291596, "median": 0.291339, "std": 0.039998, "2.5% percentile": 0.212598, "97.5% percentile": 0.370079}, "Accuracy": {"value": 0.779528, "mean": 0.778966, "median": 0.779528, "std": 0.036549, "2.5% percentile": 0.708661, "97.5% percentile": 0.850394}, "Precision0": {"value": 0.767241, "mean": 0.766722, "median": 0.767241, "std": 0.038955, "2.5% percentile": 0.6875, "97.5% percentile": 0.840708}, "Precision1": {"value": 0.909091, "mean": 0.909, "median": 0.916667, "std": 0.090288, "2.5% percentile": 0.7, "97.5% percentile": 1.0}, "Recall0": {"value": 0.988889, "mean": 0.988813, "median": 0.98913, "std": 0.011109, "2.5% percentile": 0.964286, "97.5% percentile": 1.0}, "Recall1": {"value": 0.27027, "mean": 0.269197, "median": 0.266667, "std": 0.072645, "2.5% percentile": 0.131579, "97.5% percentile": 0.416667}, "False Negative Rate": {"value": 0.72973, "mean": 0.730803, "median": 0.733333, "std": 0.072645, "2.5% percentile": 0.583333, "97.5% percentile": 0.868421}, "False Positive Rate": {"value": 0.011111, "mean": 0.011187, "median": 0.01087, "std": 0.011109, "2.5% percentile": 0.0, "97.5% percentile": 0.035714}, "Average predicted risk": {"value": 0.138944, "mean": 0.139109, "median": 0.13865, "std": 0.015371, "2.5% percentile": 0.110219, "97.5% percentile": 0.170352}, "Average observed risk": {"value": 0.291339, "mean": 0.291596, "median": 0.291339, "std": 0.039998, "2.5% percentile": 0.212598, "97.5% percentile": 0.370079}, "Difference in average predicted and observed risk": {"value": -0.152395, "mean": -0.152488, "median": -0.152148, "std": 0.031726, "2.5% percentile": -0.215676, "97.5% percentile": -0.090427}}, "Medicare": {"AUC of ROC": {"value": 0.835829, "mean": 0.835749, "median": 0.835868, "std": 0.009482, "2.5% percentile": 0.816707, "97.5% percentile": 0.853987}, "AUC of PRC": {"value": 0.655562, "mean": 0.655103, "median": 0.655378, "std": 0.020986, "2.5% percentile": 0.613314, "97.5% percentile": 0.695096}, "min(+P, Se)": {"value": 0.626335, "mean": 0.62543, "median": 0.625862, "std": 0.017249, "2.5% percentile": 0.59116, "97.5% percentile": 0.658407}, "Prevalence": {"value": 0.265877, "mean": 0.265538, "median": 0.265403, "std": 0.009501, "2.5% percentile": 0.246919, "97.5% percentile": 0.28436}, "Accuracy": {"value": 0.769194, "mean": 0.769423, "median": 0.769668, "std": 0.009078, "2.5% percentile": 0.751185, "97.5% percentile": 0.787204}, "Precision0": {"value": 0.76927, "mean": 0.769568, "median": 0.769697, "std": 0.009392, "2.5% percentile": 0.750766, "97.5% percentile": 0.787848}, "Precision1": {"value": 0.768116, "mean": 0.767389, "median": 0.768212, "std": 0.036191, "2.5% percentile": 0.693545, "97.5% percentile": 0.836739}, "Recall0": {"value": 0.979342, "mean": 0.97929, "median": 0.979408, "std": 0.003634, "2.5% percentile": 0.971992, "97.5% percentile": 0.986076}, "Recall1": {"value": 0.188948, "mean": 0.188947, "median": 0.188713, "std": 0.016473, "2.5% percentile": 0.157439, "97.5% percentile": 0.22165}, "False Negative Rate": {"value": 0.811052, "mean": 0.811053, "median": 0.811287, "std": 0.016473, "2.5% percentile": 0.77835, "97.5% percentile": 0.842561}, "False Positive Rate": {"value": 0.020658, "mean": 0.02071, "median": 0.020592, "std": 0.003634, "2.5% percentile": 0.013924, "97.5% percentile": 0.028008}, "Average predicted risk": {"value": 0.137101, "mean": 0.137079, "median": 0.137025, "std": 0.003963, "2.5% percentile": 0.129451, "97.5% percentile": 0.144956}, "Average observed risk": {"value": 0.265877, "mean": 0.265538, "median": 0.265403, "std": 0.009501, "2.5% percentile": 0.246919, "97.5% percentile": 0.28436}, "Difference in average predicted and observed risk": {"value": -0.12877599999999997, "mean": -0.128459, "median": -0.128402, "std": 0.008238, "2.5% percentile": -0.144943, "97.5% percentile": -0.112185}}, "Medicaid": {"AUC of ROC": {"value": 0.825949, "mean": 0.82613, "median": 0.826448, "std": 0.02027, "2.5% percentile": 0.784751, "97.5% percentile": 0.864184}, "AUC of PRC": {"value": 0.719022, "mean": 0.723456, "median": 0.722208, "std": 0.040211, "2.5% percentile": 0.647837, "97.5% percentile": 0.807676}, "min(+P, Se)": {"value": 0.692308, "mean": 0.692192, "median": 0.692708, "std": 0.033764, "2.5% percentile": 0.625, "97.5% percentile": 0.756098}, "Prevalence": {"value": 0.408978, "mean": 0.409011, "median": 0.408978, "std": 0.024631, "2.5% percentile": 0.361596, "97.5% percentile": 0.456359}, "Accuracy": {"value": 0.705736, "mean": 0.705604, "median": 0.705736, "std": 0.02317, "2.5% percentile": 0.660848, "97.5% percentile": 0.750623}, "Precision0": {"value": 0.674487, "mean": 0.674353, "median": 0.674556, "std": 0.025671, "2.5% percentile": 0.623907, "97.5% percentile": 0.72434}, "Precision1": {"value": 0.883333, "mean": 0.883372, "median": 0.885246, "std": 0.041501, "2.5% percentile": 0.795918, "97.5% percentile": 0.958333}, "Recall0": {"value": 0.970464, "mean": 0.970535, "median": 0.970954, "std": 0.010852, "2.5% percentile": 0.947368, "97.5% percentile": 0.991071}, "Recall1": {"value": 0.323171, "mean": 0.322817, "median": 0.322785, "std": 0.0369, "2.5% percentile": 0.251534, "97.5% percentile": 0.396453}, "False Negative Rate": {"value": 0.676829, "mean": 0.677183, "median": 0.677215, "std": 0.0369, "2.5% percentile": 0.603547, "97.5% percentile": 0.748466}, "False Positive Rate": {"value": 0.029536, "mean": 0.029465, "median": 0.029046, "std": 0.010852, "2.5% percentile": 0.008929, "97.5% percentile": 0.052632}, "Average predicted risk": {"value": 0.190689, "mean": 0.190625, "median": 0.190424, "std": 0.011491, "2.5% percentile": 0.168542, "97.5% percentile": 0.213557}, "Average observed risk": {"value": 0.408978, "mean": 0.409011, "median": 0.408978, "std": 0.024631, "2.5% percentile": 0.361596, "97.5% percentile": 0.456359}, "Difference in average predicted and observed risk": {"value": -0.218289, "mean": -0.218387, "median": -0.218294, "std": 0.021239, "2.5% percentile": -0.259843, "97.5% percentile": -0.17705}}, "Private": {"AUC of ROC": {"value": 0.887867, "mean": 0.887745, "median": 0.887829, "std": 0.008429, "2.5% percentile": 0.870816, "97.5% percentile": 0.903805}, "AUC of PRC": {"value": 0.837371, "mean": 0.837294, "median": 0.837664, "std": 0.014333, "2.5% percentile": 0.808493, "97.5% percentile": 0.864036}, "min(+P, Se)": {"value": 0.795764, "mean": 0.795795, "median": 0.79595, "std": 0.015422, "2.5% percentile": 0.76539, "97.5% percentile": 0.825077}, "Prevalence": {"value": 0.397476, "mean": 0.397579, "median": 0.397476, "std": 0.012301, "2.5% percentile": 0.373502, "97.5% percentile": 0.421467}, "Accuracy": {"value": 0.691483, "mean": 0.691363, "median": 0.691483, "std": 0.01158, "2.5% percentile": 0.668139, "97.5% percentile": 0.714196}, "Precision0": {"value": 0.665483, "mean": 0.665346, "median": 0.665272, "std": 0.012559, "2.5% percentile": 0.640251, "97.5% percentile": 0.689534}, "Precision1": {"value": 0.898305, "mean": 0.898445, "median": 0.899408, "std": 0.022966, "2.5% percentile": 0.85119, "97.5% percentile": 0.941176}, "Recall0": {"value": 0.981152, "mean": 0.981182, "median": 0.981366, "std": 0.004437, "2.5% percentile": 0.972043, "97.5% percentile": 0.989463}, "Recall1": {"value": 0.252381, "mean": 0.25222, "median": 0.252019, "std": 0.017261, "2.5% percentile": 0.21875, "97.5% percentile": 0.286154}, "False Negative Rate": {"value": 0.747619, "mean": 0.74778, "median": 0.747981, "std": 0.017261, "2.5% percentile": 0.713846, "97.5% percentile": 0.78125}, "False Positive Rate": {"value": 0.018848, "mean": 0.018818, "median": 0.018634, "std": 0.004437, "2.5% percentile": 0.010537, "97.5% percentile": 0.027957}, "Average predicted risk": {"value": 0.170612, "mean": 0.17056, "median": 0.170517, "std": 0.005517, "2.5% percentile": 0.159899, "97.5% percentile": 0.181426}, "Average observed risk": {"value": 0.397476, "mean": 0.397579, "median": 0.397476, "std": 0.012301, "2.5% percentile": 0.373502, "97.5% percentile": 0.421467}, "Difference in average predicted and observed risk": {"value": -0.22686399999999998, "mean": -0.227019, "median": -0.226815, "std": 0.010026, "2.5% percentile": -0.24698, "97.5% percentile": -0.207624}}, "Self Pay": {"AUC of ROC": {"value": 0.965261, "mean": 0.965279, "median": 0.969697, "std": 0.026073, "2.5% percentile": 0.902381, "97.5% percentile": 1.0}, "AUC of PRC": {"value": 0.909364, "mean": 0.907137, "median": 0.921653, "std": 0.078497, "2.5% percentile": 0.71249, "97.5% percentile": 1.0}, "min(+P, Se)": {"value": 0.857143, "mean": 0.868885, "median": 0.875, "std": 0.076103, "2.5% percentile": 0.7, "97.5% percentile": 1.0}, "Prevalence": {"value": 0.295455, "mean": 0.294509, "median": 0.295455, "std": 0.068302, "2.5% percentile": 0.159091, "97.5% percentile": 0.431818}, "Accuracy": {"value": 0.840909, "mean": 0.84202, "median": 0.840909, "std": 0.055187, "2.5% percentile": 0.727273, "97.5% percentile": 0.931818}, "Precision0": {"value": 0.833333, "mean": 0.834505, "median": 0.837838, "std": 0.061845, "2.5% percentile": 0.705882, "97.5% percentile": 0.945946}, "Precision1": {"value": 0.875, "mean": null, "median": null, "std": null, "2.5% percentile": null, "97.5% percentile": null}, "Recall0": {"value": 0.967742, "mean": 0.968039, "median": 0.96875, "std": 0.031818, "2.5% percentile": 0.892857, "97.5% percentile": 1.0}, "Recall1": {"value": 0.538462, "mean": 0.540175, "median": 0.538462, "std": 0.141789, "2.5% percentile": 0.25, "97.5% percentile": 0.818182}, "False Negative Rate": {"value": 0.461538, "mean": 0.459825, "median": 0.461538, "std": 0.141789, "2.5% percentile": 0.181818, "97.5% percentile": 0.75}, "False Positive Rate": {"value": 0.032258, "mean": 0.031961, "median": 0.03125, "std": 0.031818, "2.5% percentile": 0.0, "97.5% percentile": 0.107143}, "Average predicted risk": {"value": 0.228456, "mean": 0.228142, "median": 0.226888, "std": 0.044654, "2.5% percentile": 0.144331, "97.5% percentile": 0.316882}, "Average observed risk": {"value": 0.295455, "mean": 0.294509, "median": 0.295455, "std": 0.068302, "2.5% percentile": 0.159091, "97.5% percentile": 0.431818}, "Difference in average predicted and observed risk": {"value": -0.06699900000000003, "mean": -0.066368, "median": -0.065547, "std": 0.041154, "2.5% percentile": -0.148771, "97.5% percentile": 0.01052}}}, "Gender": {"F": {"AUC of ROC": {"value": 0.859233, "mean": 0.859111, "median": 0.859148, "std": 0.008969, "2.5% percentile": 0.841466, "97.5% percentile": 0.876575}, "AUC of PRC": {"value": 0.753481, "mean": 0.753387, "median": 0.753574, "std": 0.018052, "2.5% percentile": 0.717432, "97.5% percentile": 0.788089}, "min(+P, Se)": {"value": 0.671498, "mean": 0.675219, "median": 0.675044, "std": 0.016019, "2.5% percentile": 0.643697, "97.5% percentile": 0.706791}, "Prevalence": {"value": 0.323687, "mean": 0.323804, "median": 0.323687, "std": 0.010806, "2.5% percentile": 0.303323, "97.5% percentile": 0.345123}, "Accuracy": {"value": 0.754555, "mean": 0.754403, "median": 0.754555, "std": 0.009952, "2.5% percentile": 0.735263, "97.5% percentile": 0.774384}, "Precision0": {"value": 0.741297, "mean": 0.741162, "median": 0.741191, "std": 0.010675, "2.5% percentile": 0.720145, "97.5% percentile": 0.762076}, "Precision1": {"value": 0.865, "mean": 0.864599, "median": 0.865285, "std": 0.024352, "2.5% percentile": 0.814433, "97.5% percentile": 0.91045}, "Recall0": {"value": 0.978605, "mean": 0.978529, "median": 0.978622, "std": 0.004084, "2.5% percentile": 0.970289, "97.5% percentile": 0.986133}, "Recall1": {"value": 0.286424, "mean": 0.286353, "median": 0.28619, "std": 0.018542, "2.5% percentile": 0.25, "97.5% percentile": 0.323052}, "False Negative Rate": {"value": 0.713576, "mean": 0.713647, "median": 0.71381, "std": 0.018542, "2.5% percentile": 0.676948, "97.5% percentile": 0.75}, "False Positive Rate": {"value": 0.021395, "mean": 0.021471, "median": 0.021378, "std": 0.004084, "2.5% percentile": 0.013867, "97.5% percentile": 0.029711}, "Average predicted risk": {"value": 0.164978, "mean": 0.165034, "median": 0.165038, "std": 0.004925, "2.5% percentile": 0.155414, "97.5% percentile": 0.174725}, "Average observed risk": {"value": 0.323687, "mean": 0.323804, "median": 0.323687, "std": 0.010806, "2.5% percentile": 0.303323, "97.5% percentile": 0.345123}, "Difference in average predicted and observed risk": {"value": -0.158709, "mean": -0.15877, "median": -0.15876, "std": 0.00889, "2.5% percentile": -0.176132, "97.5% percentile": -0.141309}}, "M": {"AUC of ROC": {"value": 0.860148, "mean": 0.860221, "median": 0.860284, "std": 0.0077, "2.5% percentile": 0.845072, "97.5% percentile": 0.875186}, "AUC of PRC": {"value": 0.748245, "mean": 0.748367, "median": 0.74874, "std": 0.015947, "2.5% percentile": 0.716458, "97.5% percentile": 0.779096}, "min(+P, Se)": {"value": 0.702602, "mean": 0.704617, "median": 0.704797, "std": 0.013449, "2.5% percentile": 0.678074, "97.5% percentile": 0.730901}, "Prevalence": {"value": 0.333611, "mean": 0.333549, "median": 0.333611, "std": 0.009702, "2.5% percentile": 0.314452, "97.5% percentile": 0.35277}, "Accuracy": {"value": 0.720533, "mean": 0.720602, "median": 0.720533, "std": 0.009272, "2.5% percentile": 0.701791, "97.5% percentile": 0.738442}, "Precision0": {"value": 0.710467, "mean": 0.710536, "median": 0.710616, "std": 0.009756, "2.5% percentile": 0.691016, "97.5% percentile": 0.72962}, "Precision1": {"value": 0.835052, "mean": 0.835129, "median": 0.835556, "std": 0.026879, "2.5% percentile": 0.780488, "97.5% percentile": 0.88601}, "Recall0": {"value": 0.98, "mean": 0.980014, "median": 0.980124, "std": 0.003524, "2.5% percentile": 0.97289, "97.5% percentile": 0.986503}, "Recall1": {"value": 0.202247, "mean": 0.202281, "median": 0.202206, "std": 0.014432, "2.5% percentile": 0.174311, "97.5% percentile": 0.231144}, "False Negative Rate": {"value": 0.797753, "mean": 0.797719, "median": 0.797794, "std": 0.014432, "2.5% percentile": 0.768856, "97.5% percentile": 0.825689}, "False Positive Rate": {"value": 0.02, "mean": 0.019986, "median": 0.019876, "std": 0.003524, "2.5% percentile": 0.013497, "97.5% percentile": 0.02711}, "Average predicted risk": {"value": 0.148279, "mean": 0.148283, "median": 0.148238, "std": 0.004098, "2.5% percentile": 0.140311, "97.5% percentile": 0.15639}, "Average observed risk": {"value": 0.333611, "mean": 0.333549, "median": 0.333611, "std": 0.009702, "2.5% percentile": 0.314452, "97.5% percentile": 0.35277}, "Difference in average predicted and observed risk": {"value": -0.185332, "mean": -0.185267, "median": -0.185184, "std": 0.008226, "2.5% percentile": -0.201617, "97.5% percentile": -0.169016}}}, "Ethnicity": {"OTHER": {"AUC of ROC": {"value": 0.881811, "mean": 0.881625, "median": 0.882086, "std": 0.013885, "2.5% percentile": 0.853037, "97.5% percentile": 0.907737}, "AUC of PRC": {"value": 0.835911, "mean": 0.836024, "median": 0.837284, "std": 0.023802, "2.5% percentile": 0.786573, "97.5% percentile": 0.878658}, "min(+P, Se)": {"value": 0.794677, "mean": 0.792557, "median": 0.793103, "std": 0.020011, "2.5% percentile": 0.751969, "97.5% percentile": 0.830325}, "Prevalence": {"value": 0.410658, "mean": 0.411135, "median": 0.410658, "std": 0.019602, "2.5% percentile": 0.373041, "97.5% percentile": 0.449843}, "Accuracy": {"value": 0.69279, "mean": 0.692609, "median": 0.69279, "std": 0.018361, "2.5% percentile": 0.65674, "97.5% percentile": 0.72884}, "Precision0": {"value": 0.662455, "mean": 0.662132, "median": 0.662021, "std": 0.020229, "2.5% percentile": 0.622503, "97.5% percentile": 0.701439}, "Precision1": {"value": 0.892857, "mean": 0.893058, "median": 0.895349, "std": 0.034137, "2.5% percentile": 0.820225, "97.5% percentile": 0.954023}, "Recall0": {"value": 0.976064, "mean": 0.97604, "median": 0.97644, "std": 0.007925, "2.5% percentile": 0.95935, "97.5% percentile": 0.989637}, "Recall1": {"value": 0.28626, "mean": 0.286662, "median": 0.28626, "std": 0.027863, "2.5% percentile": 0.23346, "97.5% percentile": 0.343286}, "False Negative Rate": {"value": 0.71374, "mean": 0.713338, "median": 0.71374, "std": 0.027863, "2.5% percentile": 0.656714, "97.5% percentile": 0.76654}, "False Positive Rate": {"value": 0.023936, "mean": 0.02396, "median": 0.02356, "std": 0.007925, "2.5% percentile": 0.010363, "97.5% percentile": 0.04065}, "Average predicted risk": {"value": 0.191792, "mean": 0.191986, "median": 0.191739, "std": 0.009323, "2.5% percentile": 0.174013, "97.5% percentile": 0.210386}, "Average observed risk": {"value": 0.410658, "mean": 0.411135, "median": 0.410658, "std": 0.019602, "2.5% percentile": 0.373041, "97.5% percentile": 0.449843}, "Difference in average predicted and observed risk": {"value": -0.21886600000000003, "mean": -0.219148, "median": -0.218962, "std": 0.015666, "2.5% percentile": -0.25053, "97.5% percentile": -0.18847}}, "ASIAN": {"AUC of ROC": {"value": 0.840502, "mean": 0.840298, "median": 0.84316, "std": 0.04717, "2.5% percentile": 0.742421, "97.5% percentile": 0.926286}, "AUC of PRC": {"value": 0.675224, "mean": 0.674096, "median": 0.675928, "std": 0.086598, "2.5% percentile": 0.495803, "97.5% percentile": 0.835697}, "min(+P, Se)": {"value": 0.757576, "mean": 0.750694, "median": 0.756098, "std": 0.066735, "2.5% percentile": 0.611111, "97.5% percentile": 0.870968}, "Prevalence": {"value": 0.364706, "mean": 0.364014, "median": 0.364706, "std": 0.052526, "2.5% percentile": 0.258824, "97.5% percentile": 0.470588}, "Accuracy": {"value": 0.647059, "mean": 0.648038, "median": 0.647059, "std": 0.052129, "2.5% percentile": 0.541176, "97.5% percentile": 0.752941}, "Precision0": {"value": 0.657895, "mean": 0.658724, "median": 0.658228, "std": 0.054757, "2.5% percentile": 0.547937, "97.5% percentile": 0.763158}, "Precision1": {"value": 0.555556, "mean": null, "median": null, "std": null, "2.5% percentile": null, "97.5% percentile": null}, "Recall0": {"value": 0.925926, "mean": 0.926506, "median": 0.928571, "std": 0.035619, "2.5% percentile": 0.85, "97.5% percentile": 0.982759}, "Recall1": {"value": 0.16129, "mean": 0.161402, "median": 0.15625, "std": 0.066987, "2.5% percentile": 0.037037, "97.5% percentile": 0.3}, "False Negative Rate": {"value": 0.83871, "mean": 0.838598, "median": 0.84375, "std": 0.066987, "2.5% percentile": 0.7, "97.5% percentile": 0.962963}, "False Positive Rate": {"value": 0.074074, "mean": 0.073494, "median": 0.071429, "std": 0.035619, "2.5% percentile": 0.017241, "97.5% percentile": 0.15}, "Average predicted risk": {"value": 0.218089, "mean": 0.21776, "median": 0.217034, "std": 0.023943, "2.5% percentile": 0.172065, "97.5% percentile": 0.265891}, "Average observed risk": {"value": 0.364706, "mean": 0.364014, "median": 0.364706, "std": 0.052526, "2.5% percentile": 0.258824, "97.5% percentile": 0.470588}, "Difference in average predicted and observed risk": {"value": -0.14661699999999997, "mean": -0.146254, "median": -0.146024, "std": 0.04473, "2.5% percentile": -0.23425, "97.5% percentile": -0.058112}}, "BLACK": {"AUC of ROC": {"value": 0.803435, "mean": 0.8036, "median": 0.804448, "std": 0.024015, "2.5% percentile": 0.755201, "97.5% percentile": 0.84902}, "AUC of PRC": {"value": 0.564986, "mean": 0.565816, "median": 0.565487, "std": 0.050196, "2.5% percentile": 0.467691, "97.5% percentile": 0.662939}, "min(+P, Se)": {"value": 0.66055, "mean": 0.653203, "median": 0.654867, "std": 0.040425, "2.5% percentile": 0.571429, "97.5% percentile": 0.72807}, "Prevalence": {"value": 0.288043, "mean": 0.288096, "median": 0.288043, "std": 0.023484, "2.5% percentile": 0.241848, "97.5% percentile": 0.334239}, "Accuracy": {"value": 0.714674, "mean": 0.714616, "median": 0.714674, "std": 0.023423, "2.5% percentile": 0.668478, "97.5% percentile": 0.76087}, "Precision0": {"value": 0.718663, "mean": 0.718595, "median": 0.719101, "std": 0.023593, "2.5% percentile": 0.671388, "97.5% percentile": 0.763889}, "Precision1": {"value": 0.555556, "mean": null, "median": null, "std": null, "2.5% percentile": null, "97.5% percentile": null}, "Recall0": {"value": 0.984733, "mean": 0.984754, "median": 0.984962, "std": 0.007624, "2.5% percentile": 0.968254, "97.5% percentile": 0.99635}, "Recall1": {"value": 0.04717, "mean": 0.047071, "median": 0.045455, "std": 0.020551, "2.5% percentile": 0.009901, "97.5% percentile": 0.092441}, "False Negative Rate": {"value": 0.95283, "mean": 0.952929, "median": 0.954545, "std": 0.020551, "2.5% percentile": 0.907559, "97.5% percentile": 0.990099}, "False Positive Rate": {"value": 0.015267, "mean": 0.015246, "median": 0.015038, "std": 0.007624, "2.5% percentile": 0.00365, "97.5% percentile": 0.031746}, "Average predicted risk": {"value": 0.106981, "mean": 0.106983, "median": 0.106826, "std": 0.007431, "2.5% percentile": 0.092759, "97.5% percentile": 0.122228}, "Average observed risk": {"value": 0.288043, "mean": 0.288096, "median": 0.288043, "std": 0.023484, "2.5% percentile": 0.241848, "97.5% percentile": 0.334239}, "Difference in average predicted and observed risk": {"value": -0.181062, "mean": -0.181113, "median": -0.180479, "std": 0.021661, "2.5% percentile": -0.224056, "97.5% percentile": -0.140033}}, "HISPANIC": {"AUC of ROC": {"value": 0.923351, "mean": 0.923142, "median": 0.924804, "std": 0.024229, "2.5% percentile": 0.870476, "97.5% percentile": 0.966168}, "AUC of PRC": {"value": 0.802281, "mean": 0.800008, "median": 0.80578, "std": 0.064409, "2.5% percentile": 0.658293, "97.5% percentile": 0.908016}, "min(+P, Se)": {"value": 0.763158, "mean": 0.763952, "median": 0.766667, "std": 0.063537, "2.5% percentile": 0.631579, "97.5% percentile": 0.878067}, "Prevalence": {"value": 0.244444, "mean": 0.244465, "median": 0.244444, "std": 0.037434, "2.5% percentile": 0.17037, "97.5% percentile": 0.318519}, "Accuracy": {"value": 0.814815, "mean": 0.814689, "median": 0.814815, "std": 0.033667, "2.5% percentile": 0.748148, "97.5% percentile": 0.881481}, "Precision0": {"value": 0.823529, "mean": 0.82367, "median": 0.824561, "std": 0.035333, "2.5% percentile": 0.754095, "97.5% percentile": 0.890756}, "Precision1": {"value": 0.75, "mean": 0.747879, "median": 0.75, "std": 0.112474, "2.5% percentile": 0.5, "97.5% percentile": 0.941176}, "Recall0": {"value": 0.960784, "mean": 0.960331, "median": 0.961165, "std": 0.019336, "2.5% percentile": 0.918905, "97.5% percentile": 0.990566}, "Recall1": {"value": 0.363636, "mean": 0.364651, "median": 0.363636, "std": 0.085462, "2.5% percentile": 0.2, "97.5% percentile": 0.538462}, "False Negative Rate": {"value": 0.636364, "mean": 0.635349, "median": 0.636364, "std": 0.085462, "2.5% percentile": 0.461538, "97.5% percentile": 0.8}, "False Positive Rate": {"value": 0.039216, "mean": 0.039669, "median": 0.038835, "std": 0.019336, "2.5% percentile": 0.009434, "97.5% percentile": 0.081095}, "Average predicted risk": {"value": 0.170764, "mean": 0.171142, "median": 0.170666, "std": 0.021006, "2.5% percentile": 0.131106, "97.5% percentile": 0.213279}, "Average observed risk": {"value": 0.244444, "mean": 0.244465, "median": 0.244444, "std": 0.037434, "2.5% percentile": 0.17037, "97.5% percentile": 0.318519}, "Difference in average predicted and observed risk": {"value": -0.07368, "mean": -0.073324, "median": -0.072876, "std": 0.028327, "2.5% percentile": -0.129483, "97.5% percentile": -0.018971}}, "WHITE": {"AUC of ROC": {"value": 0.85712, "mean": 0.857196, "median": 0.85726, "std": 0.006945, "2.5% percentile": 0.843425, "97.5% percentile": 0.870652}, "AUC of PRC": {"value": 0.739117, "mean": 0.739257, "median": 0.739402, "std": 0.014545, "2.5% percentile": 0.710123, "97.5% percentile": 0.767407}, "min(+P, Se)": {"value": 0.662944, "mean": 0.667406, "median": 0.667668, "std": 0.012346, "2.5% percentile": 0.643044, "97.5% percentile": 0.691761}, "Prevalence": {"value": 0.319961, "mean": 0.319885, "median": 0.319632, "std": 0.008524, "2.5% percentile": 0.30319, "97.5% percentile": 0.336731}, "Accuracy": {"value": 0.745807, "mean": 0.745931, "median": 0.745807, "std": 0.007963, "2.5% percentile": 0.730352, "97.5% percentile": 0.761592}, "Precision0": {"value": 0.734177, "mean": 0.734287, "median": 0.734344, "std": 0.008481, "2.5% percentile": 0.717716, "97.5% percentile": 0.750725}, "Precision1": {"value": 0.862319, "mean": 0.862566, "median": 0.863014, "std": 0.020874, "2.5% percentile": 0.821168, "97.5% percentile": 0.902725}, "Recall0": {"value": 0.981625, "mean": 0.981662, "median": 0.981731, "std": 0.002947, "2.5% percentile": 0.975783, "97.5% percentile": 0.987267}, "Recall1": {"value": 0.244604, "mean": 0.244743, "median": 0.244659, "std": 0.013878, "2.5% percentile": 0.217701, "97.5% percentile": 0.271875}, "False Negative Rate": {"value": 0.755396, "mean": 0.755257, "median": 0.755341, "std": 0.013878, "2.5% percentile": 0.728125, "97.5% percentile": 0.782299}, "False Positive Rate": {"value": 0.018375, "mean": 0.018338, "median": 0.018269, "std": 0.002947, "2.5% percentile": 0.012733, "97.5% percentile": 0.024217}, "Average predicted risk": {"value": 0.151445, "mean": 0.151431, "median": 0.151375, "std": 0.00362, "2.5% percentile": 0.144484, "97.5% percentile": 0.158552}, "Average observed risk": {"value": 0.319961, "mean": 0.319885, "median": 0.319632, "std": 0.008524, "2.5% percentile": 0.30319, "97.5% percentile": 0.336731}, "Difference in average predicted and observed risk": {"value": -0.168516, "mean": -0.168454, "median": -0.16839, "std": 0.007177, "2.5% percentile": -0.182807, "97.5% percentile": -0.154562}}}}